ordflow/__init__.py
ordflow/__version__.py
ordflow/api.py
ordflow-0.0.2.dist-info/METADATA
ordflow-0.0.2.dist-info/RECORD
ordflow-0.0.2.dist-info/WHEEL
ordflow-0.0.2.dist-info/top_level.txt
